[
  {
    "username": "testBruger",
    "email": "test@test.dk",
    "password": "$2b$10$2uWCBjWQKs5evsy.OWGH/emQu/EAKNZuzXj8BNybyfUZvmrmXbEWK",
    "role_id": "user"
  },
  {
    "username": "testBruger2",
    "email": "test2@test.dk",
    "password": "$2b$10$H0TCFWB7jBcBRBzL22ED5.fM6uluexdWm0LQDccrh1pFJ1A6ZuiRK",
    "role_id": "user"
  },
  {
    "username": "testAdmin",
    "email": "admin@test.dk",
    "password": "$2b$10$2uWCBjWQKs5evsy.OWGH/emQu/EAKNZuzXj8BNybyfUZvmrmXbEWK",
    "role_id": "admin"
  }
]
